smart_redis_storage/__init__.py
smart_redis_storage/redis_storage.py
smart_redis_storage-0.1.3.dist-info/licenses/LICENSE
smart_redis_storage-0.1.3.dist-info/METADATA
smart_redis_storage-0.1.3.dist-info/WHEEL
smart_redis_storage-0.1.3.dist-info/top_level.txt
smart_redis_storage-0.1.3.dist-info/RECORD
