Metadata-Version: 2.4
Name: smart-redis-storage
Version: 0.1.3
Summary: Convenient work with Redis.
Home-page: https://github.com/smartlegionlab/smart-redis-storage/
Author: A.A. Suvorov
Author-email: smartlegiondev@gmail.com
License: BSD 3-Clause License
Project-URL: Documentation, https://github.com/smartlegionlab/smart-redis-storage/blob/master/README.md
Project-URL: Release notes, https://github.com/smartlegionlab/smart-redis-storage/releases
Keywords: redis,django,smartlegionlab,redis storage,redis storage manager
Classifier: Development Status :: 5 - Production/Stable
Classifier: License :: OSI Approved :: BSD License
Classifier: Natural Language :: English
Classifier: Operating System :: OS Independent
Classifier: Operating System :: POSIX :: Linux
Classifier: Programming Language :: Python :: 3 :: Only
Classifier: Topic :: Software Development :: Libraries :: Python Modules
Requires-Python: >=3.6
License-File: LICENSE
Requires-Dist: redis~=5.0.4
Dynamic: license-file
